tools.py
liyichenglib/__init__.py
liyichenglib/lyc1.py
liyichenglib666-1.0.0.dist-info/LICENSE.txt
liyichenglib666-1.0.0.dist-info/METADATA
liyichenglib666-1.0.0.dist-info/WHEEL
liyichenglib666-1.0.0.dist-info/top_level.txt
liyichenglib666-1.0.0.dist-info/RECORD
