Metadata-Version: 2.1
Name: liyichenglib666
Version: 1.0.0
Summary: this is a test lib for study
Home-page: https://www.baidu.com
Author: liyicheng
Author-email: leeyc7@foxmail.com
License: MIT
Platform: UNKNOWN
